{"items":[{"t":"C","n":"App\\Http\\Controllers\\Auth\\ConfirmPasswordController","p":"App/Http/Controllers/Auth/ConfirmPasswordController.html","d":null,"f":{"n":"App\\Http\\Controllers\\Auth","p":"App/Http/Controllers/Auth.html"}},{"t":"C","n":"App\\Http\\Controllers\\Auth\\ForgotPasswordController","p":"App/Http/Controllers/Auth/ForgotPasswordController.html","d":null,"f":{"n":"App\\Http\\Controllers\\Auth","p":"App/Http/Controllers/Auth.html"}},{"t":"C","n":"App\\Http\\Controllers\\Auth\\LoginController","p":"App/Http/Controllers/Auth/LoginController.html","d":"<p>Controlador que maneja la autenticaci\u00f3n de usuarios</p>","f":{"n":"App\\Http\\Controllers\\Auth","p":"App/Http/Controllers/Auth.html"}},{"t":"C","n":"App\\Http\\Controllers\\Auth\\RegisterController","p":"App/Http/Controllers/Auth/RegisterController.html","d":"<p>Controlador para el registro de nuevos usuarios</p>","f":{"n":"App\\Http\\Controllers\\Auth","p":"App/Http/Controllers/Auth.html"}},{"t":"C","n":"App\\Http\\Controllers\\Auth\\ResetPasswordController","p":"App/Http/Controllers/Auth/ResetPasswordController.html","d":"<p>Controlador para el restablecimiento de contrase\u00f1as</p>","f":{"n":"App\\Http\\Controllers\\Auth","p":"App/Http/Controllers/Auth.html"}},{"t":"C","n":"App\\Http\\Controllers\\Auth\\VerificationController","p":"App/Http/Controllers/Auth/VerificationController.html","d":"<p>Controlador para la verificaci\u00f3n de correo electr\u00f3nico</p>","f":{"n":"App\\Http\\Controllers\\Auth","p":"App/Http/Controllers/Auth.html"}},{"t":"C","n":"App\\Http\\Controllers\\BitacoracambioController","p":"App/Http/Controllers/BitacoracambioController.html","d":"<p>Controlador para gestionar las operaciones relacionadas con la bit\u00e1cora de cambios</p>","f":{"n":"App\\Http\\Controllers","p":"App/Http/Controllers.html"}},{"t":"C","n":"App\\Http\\Controllers\\ClienteController","p":"App/Http/Controllers/ClienteController.html","d":"<p>Controlador para la gesti\u00f3n de clientes</p>","f":{"n":"App\\Http\\Controllers","p":"App/Http/Controllers.html"}},{"t":"C","n":"App\\Http\\Controllers\\Controller","p":"App/Http/Controllers/Controller.html","d":"<p>Este controlador es la clase base de todos los controladores de la aplicaci\u00f3n\naportando funcionalidades comunes a todos ellos</p>","f":{"n":"App\\Http\\Controllers","p":"App/Http/Controllers.html"}},{"t":"C","n":"App\\Http\\Controllers\\EmpleadoController","p":"App/Http/Controllers/EmpleadoController.html","d":"<p>Controlador para la gesti\u00f3n de empleados</p>","f":{"n":"App\\Http\\Controllers","p":"App/Http/Controllers.html"}},{"t":"C","n":"App\\Http\\Controllers\\HomeController","p":"App/Http/Controllers/HomeController.html","d":"<p>Controlador para la p\u00e1gina de inicio del sistema</p>","f":{"n":"App\\Http\\Controllers","p":"App/Http/Controllers.html"}},{"t":"C","n":"App\\Http\\Controllers\\InformacionEmpresaController","p":"App/Http/Controllers/InformacionEmpresaController.html","d":"<p>Controlador para la gesti\u00f3n de la informaci\u00f3n de la empresa</p>","f":{"n":"App\\Http\\Controllers","p":"App/Http/Controllers.html"}},{"t":"C","n":"App\\Http\\Controllers\\MembresiaController","p":"App/Http/Controllers/MembresiaController.html","d":"<p>Controlador para la gesti\u00f3n de membres\u00edas</p>","f":{"n":"App\\Http\\Controllers","p":"App/Http/Controllers.html"}},{"t":"C","n":"App\\Http\\Controllers\\PagoController","p":"App/Http/Controllers/PagoController.html","d":"<p>Controlador para la gesti\u00f3n de pagos</p>","f":{"n":"App\\Http\\Controllers","p":"App/Http/Controllers.html"}},{"t":"C","n":"App\\Http\\Controllers\\PagodetallController","p":"App/Http/Controllers/PagodetallController.html","d":null,"f":{"n":"App\\Http\\Controllers","p":"App/Http/Controllers.html"}},{"t":"C","n":"App\\Http\\Controllers\\PermisoController","p":"App/Http/Controllers/PermisoController.html","d":"<p>Controlador para la gesti\u00f3n de permisos del sistema</p>","f":{"n":"App\\Http\\Controllers","p":"App/Http/Controllers.html"}},{"t":"C","n":"App\\Http\\Controllers\\ProfileController","p":"App/Http/Controllers/ProfileController.html","d":"<p>Controlador para la gesti\u00f3n del perfil de usuario</p>","f":{"n":"App\\Http\\Controllers","p":"App/Http/Controllers.html"}},{"t":"C","n":"App\\Http\\Controllers\\ReporteController","p":"App/Http/Controllers/ReporteController.html","d":"<p>Controlador para la generaci\u00f3n de reportes PDF del sistema.</p>","f":{"n":"App\\Http\\Controllers","p":"App/Http/Controllers.html"}},{"t":"C","n":"App\\Http\\Controllers\\RolController","p":"App/Http/Controllers/RolController.html","d":"<p>Controlador para la gesti\u00f3n de roles</p>","f":{"n":"App\\Http\\Controllers","p":"App/Http/Controllers.html"}},{"t":"C","n":"App\\Http\\Controllers\\RolporpermisoController","p":"App/Http/Controllers/RolporpermisoController.html","d":"<p>Controlador para la gesti\u00f3n de los roles por permisos de usuario en la aplicaci\u00f3n</p>","f":{"n":"App\\Http\\Controllers","p":"App/Http/Controllers.html"}},{"t":"C","n":"App\\Http\\Controllers\\UserController","p":"App/Http/Controllers/UserController.html","d":"<p>Controlador para la gesti\u00f3n de usuarios</p>","f":{"n":"App\\Http\\Controllers","p":"App/Http/Controllers.html"}},{"t":"C","n":"App\\Http\\Middleware\\Authenticate","p":"App/Http/Middleware/Authenticate.html","d":"<p>Middleware de autenticaci\u00f3n personalizado</p>","f":{"n":"App\\Http\\Middleware","p":"App/Http/Middleware.html"}},{"t":"C","n":"App\\Http\\Middleware\\CheckPermiso","p":"App/Http/Middleware/CheckPermiso.html","d":"<p>Middleware para verificaci\u00f3n de permisos</p>","f":{"n":"App\\Http\\Middleware","p":"App/Http/Middleware.html"}},{"t":"C","n":"App\\Http\\Requests\\BitacoracambioRequest","p":"App/Http/Requests/BitacoracambioRequest.html","d":"<p>Request personalizado para la validaci\u00f3n de bit\u00e1cora de cambios</p>","f":{"n":"App\\Http\\Requests","p":"App/Http/Requests.html"}},{"t":"C","n":"App\\Http\\Requests\\ClienteRequest","p":"App/Http/Requests/ClienteRequest.html","d":"<p>Request personalizado para la validaci\u00f3n de datos de cliente</p>","f":{"n":"App\\Http\\Requests","p":"App/Http/Requests.html"}},{"t":"C","n":"App\\Http\\Requests\\EmpleadoRequest","p":"App/Http/Requests/EmpleadoRequest.html","d":"<p>Request personalizado para la validaci\u00f3n de datos de empleados</p>","f":{"n":"App\\Http\\Requests","p":"App/Http/Requests.html"}},{"t":"C","n":"App\\Http\\Requests\\MembresiaRequest","p":"App/Http/Requests/MembresiaRequest.html","d":"<p>Request personalizado para la validaci\u00f3n de datos de membres\u00edas</p>","f":{"n":"App\\Http\\Requests","p":"App/Http/Requests.html"}},{"t":"C","n":"App\\Http\\Requests\\PagoRequest","p":"App/Http/Requests/PagoRequest.html","d":"<p>Request personalizado para la validaci\u00f3n de pagos</p>","f":{"n":"App\\Http\\Requests","p":"App/Http/Requests.html"}},{"t":"C","n":"App\\Http\\Requests\\PagodetallRequest","p":"App/Http/Requests/PagodetallRequest.html","d":"<p>Request personalizado para la validaci\u00f3n de detalles de pago</p>","f":{"n":"App\\Http\\Requests","p":"App/Http/Requests.html"}},{"t":"C","n":"App\\Http\\Requests\\PermisoRequest","p":"App/Http/Requests/PermisoRequest.html","d":"<p>Request personalizado para la validaci\u00f3n de permisos</p>","f":{"n":"App\\Http\\Requests","p":"App/Http/Requests.html"}},{"t":"C","n":"App\\Http\\Requests\\RolRequest","p":"App/Http/Requests/RolRequest.html","d":"<p>Request personalizado para la validaci\u00f3n de roles</p>","f":{"n":"App\\Http\\Requests","p":"App/Http/Requests.html"}},{"t":"C","n":"App\\Http\\Requests\\RolporpermisoRequest","p":"App/Http/Requests/RolporpermisoRequest.html","d":"<p>Request personalizado para la validaci\u00f3n de asignaci\u00f3n de permisos a roles</p>","f":{"n":"App\\Http\\Requests","p":"App/Http/Requests.html"}},{"t":"C","n":"App\\Models\\Bitacoracambio","p":"App/Models/Bitacoracambio.html","d":"<p>Modelo para el registro de cambios en la bit\u00e1cora del sistema</p>","f":{"n":"App\\Models","p":"App/Models.html"}},{"t":"C","n":"App\\Models\\Cliente","p":"App/Models/Cliente.html","d":"<p>Modelo para la gesti\u00f3n de clientes del gimnasio</p>","f":{"n":"App\\Models","p":"App/Models.html"}},{"t":"C","n":"App\\Models\\Empleado","p":"App/Models/Empleado.html","d":"<p>Modelo para la gesti\u00f3n de empleados del gimnasio</p>","f":{"n":"App\\Models","p":"App/Models.html"}},{"t":"C","n":"App\\Models\\InformacionEmpresa","p":"App/Models/InformacionEmpresa.html","d":null,"f":{"n":"App\\Models","p":"App/Models.html"}},{"t":"C","n":"App\\Models\\Membresia","p":"App/Models/Membresia.html","d":"<p>Class Membresia</p>","f":{"n":"App\\Models","p":"App/Models.html"}},{"t":"C","n":"App\\Models\\Pago","p":"App/Models/Pago.html","d":"<p>Class Pago</p>","f":{"n":"App\\Models","p":"App/Models.html"}},{"t":"C","n":"App\\Models\\Pagodetall","p":"App/Models/Pagodetall.html","d":"<p>Class Pagodetall</p>","f":{"n":"App\\Models","p":"App/Models.html"}},{"t":"C","n":"App\\Models\\Permiso","p":"App/Models/Permiso.html","d":"<p>Class Permiso</p>","f":{"n":"App\\Models","p":"App/Models.html"}},{"t":"C","n":"App\\Models\\Rol","p":"App/Models/Rol.html","d":"<p>Class Rol</p>","f":{"n":"App\\Models","p":"App/Models.html"}},{"t":"C","n":"App\\Models\\Rolporpermiso","p":"App/Models/Rolporpermiso.html","d":"<p>Class Rolporpermiso</p>","f":{"n":"App\\Models","p":"App/Models.html"}},{"t":"C","n":"App\\Models\\User","p":"App/Models/User.html","d":"<p>Modelo para la gesti\u00f3n de usuarios del sistema</p>","f":{"n":"App\\Models","p":"App/Models.html"}},{"t":"C","n":"App\\Providers\\AppServiceProvider","p":"App/Providers/AppServiceProvider.html","d":"<p>Proveedor de servicios principal de la aplicaci\u00f3n</p>","f":{"n":"App\\Providers","p":"App/Providers.html"}},{"t":"T","n":"App\\Traits\\RegistraBitacora","p":"App/Traits/RegistraBitacora.html","d":"<p>Trait para el registro autom\u00e1tico de cambios en la bit\u00e1cora</p>","f":{"n":"App\\Traits","p":"App/Traits.html"}},{"t":"M","n":"App\\Http\\Controllers\\Auth\\ConfirmPasswordController::__construct","p":"App/Http/Controllers/Auth/ConfirmPasswordController.html#method___construct","d":"<p>Crear una nueva instancia de controlador. en este caso, el middleware de autenticaci\u00f3n.</p>"},{"t":"M","n":"App\\Http\\Controllers\\Auth\\LoginController::__construct","p":"App/Http/Controllers/Auth/LoginController.html#method___construct","d":"<p>Crea una nueva instancia del controlador</p>"},{"t":"M","n":"App\\Http\\Controllers\\Auth\\RegisterController::__construct","p":"App/Http/Controllers/Auth/RegisterController.html#method___construct","d":"<p>Crea una nueva instancia del controlador</p>"},{"t":"M","n":"App\\Http\\Controllers\\Auth\\RegisterController::validator","p":"App/Http/Controllers/Auth/RegisterController.html#method_validator","d":"<p>Obtiene un validador para la solicitud de registro</p>"},{"t":"M","n":"App\\Http\\Controllers\\Auth\\RegisterController::create","p":"App/Http/Controllers/Auth/RegisterController.html#method_create","d":"<p>Crea una nueva instancia de usuario despu\u00e9s de un registro v\u00e1lido</p>"},{"t":"M","n":"App\\Http\\Controllers\\Auth\\VerificationController::__construct","p":"App/Http/Controllers/Auth/VerificationController.html#method___construct","d":"<p>Crea una nueva instancia del controlador</p>"},{"t":"M","n":"App\\Http\\Controllers\\BitacoracambioController::index","p":"App/Http/Controllers/BitacoracambioController.html#method_index","d":"<p>Muestra el listado de la bit\u00e1cora de cambios</p>"},{"t":"M","n":"App\\Http\\Controllers\\BitacoracambioController::show","p":"App/Http/Controllers/BitacoracambioController.html#method_show","d":"<p>Muestra los detalles de un registro espec\u00edfico de la bit\u00e1cora</p>"},{"t":"M","n":"App\\Http\\Controllers\\ClienteController::index","p":"App/Http/Controllers/ClienteController.html#method_index","d":null},{"t":"M","n":"App\\Http\\Controllers\\ClienteController::create","p":"App/Http/Controllers/ClienteController.html#method_create","d":"<p>Muestra el formulario para crear un nuevo cliente</p>"},{"t":"M","n":"App\\Http\\Controllers\\ClienteController::store","p":"App/Http/Controllers/ClienteController.html#method_store","d":"<p>Almacena un nuevo cliente en la base de datos</p>"},{"t":"M","n":"App\\Http\\Controllers\\ClienteController::show","p":"App/Http/Controllers/ClienteController.html#method_show","d":"<p>Display the specified resource.</p>"},{"t":"M","n":"App\\Http\\Controllers\\ClienteController::edit","p":"App/Http/Controllers/ClienteController.html#method_edit","d":"<p>Show the form for editing the specified resource.</p>"},{"t":"M","n":"App\\Http\\Controllers\\ClienteController::update","p":"App/Http/Controllers/ClienteController.html#method_update","d":"<p>Actualiza los datos de un cliente espec\u00edfico en la base de datos</p>"},{"t":"M","n":"App\\Http\\Controllers\\ClienteController::destroy","p":"App/Http/Controllers/ClienteController.html#method_destroy","d":"<p>Elimina un cliente espec\u00edfico del sistema</p>"},{"t":"M","n":"App\\Http\\Controllers\\EmpleadoController::index","p":"App/Http/Controllers/EmpleadoController.html#method_index","d":"<p>Muestra el listado de empleados</p>"},{"t":"M","n":"App\\Http\\Controllers\\EmpleadoController::create","p":"App/Http/Controllers/EmpleadoController.html#method_create","d":"<p>Muestra el formulario para crear un nuevo empleado</p>"},{"t":"M","n":"App\\Http\\Controllers\\EmpleadoController::store","p":"App/Http/Controllers/EmpleadoController.html#method_store","d":"<p>Almacena un nuevo empleado en la base de datos</p>"},{"t":"M","n":"App\\Http\\Controllers\\EmpleadoController::show","p":"App/Http/Controllers/EmpleadoController.html#method_show","d":"<p>Muestra los detalles de un empleado</p>"},{"t":"M","n":"App\\Http\\Controllers\\EmpleadoController::edit","p":"App/Http/Controllers/EmpleadoController.html#method_edit","d":"<p>Muestra el formulario para editar un empleado</p>"},{"t":"M","n":"App\\Http\\Controllers\\EmpleadoController::update","p":"App/Http/Controllers/EmpleadoController.html#method_update","d":"<p>Actualiza los datos de un empleado en la base de datos</p>"},{"t":"M","n":"App\\Http\\Controllers\\EmpleadoController::destroy","p":"App/Http/Controllers/EmpleadoController.html#method_destroy","d":"<p>Elimina un empleado de la base de datos</p>"},{"t":"M","n":"App\\Http\\Controllers\\HomeController::__construct","p":"App/Http/Controllers/HomeController.html#method___construct","d":"<p>Muestra la p\u00e1gina de inicio del sistema</p>"},{"t":"M","n":"App\\Http\\Controllers\\HomeController::index","p":"App/Http/Controllers/HomeController.html#method_index","d":"<p>Muestra la p\u00e1gina de inicio del sistema</p>"},{"t":"M","n":"App\\Http\\Controllers\\InformacionEmpresaController::index","p":"App/Http/Controllers/InformacionEmpresaController.html#method_index","d":"<p>Muestra la informaci\u00f3n de la empresa</p>"},{"t":"M","n":"App\\Http\\Controllers\\InformacionEmpresaController::create","p":"App/Http/Controllers/InformacionEmpresaController.html#method_create","d":"<p>Muestra el formulario para crear un nuevo recurso.</p>"},{"t":"M","n":"App\\Http\\Controllers\\InformacionEmpresaController::store","p":"App/Http/Controllers/InformacionEmpresaController.html#method_store","d":"<p>Almacena un nuevo recurso en la base de datos.</p>"},{"t":"M","n":"App\\Http\\Controllers\\InformacionEmpresaController::show","p":"App/Http/Controllers/InformacionEmpresaController.html#method_show","d":"<p>Muestra el recurso especificado.</p>"},{"t":"M","n":"App\\Http\\Controllers\\InformacionEmpresaController::edit","p":"App/Http/Controllers/InformacionEmpresaController.html#method_edit","d":"<p>Muestra el formulario para editar el recurso especificado.</p>"},{"t":"M","n":"App\\Http\\Controllers\\InformacionEmpresaController::__construct","p":"App/Http/Controllers/InformacionEmpresaController.html#method___construct","d":null},{"t":"M","n":"App\\Http\\Controllers\\InformacionEmpresaController::update","p":"App/Http/Controllers/InformacionEmpresaController.html#method_update","d":"<p>Actualiza los datos de la empresa en la base de datos</p>"},{"t":"M","n":"App\\Http\\Controllers\\InformacionEmpresaController::destroy","p":"App/Http/Controllers/InformacionEmpresaController.html#method_destroy","d":"<p>Elimina el recurso especificado de la base de datos.</p>"},{"t":"M","n":"App\\Http\\Controllers\\MembresiaController::index","p":"App/Http/Controllers/MembresiaController.html#method_index","d":"<p>Muestra el listado de membres\u00edas disponibles</p>"},{"t":"M","n":"App\\Http\\Controllers\\MembresiaController::create","p":"App/Http/Controllers/MembresiaController.html#method_create","d":"<p>Muestra el formulario para crear una nueva membres\u00eda</p>"},{"t":"M","n":"App\\Http\\Controllers\\MembresiaController::store","p":"App/Http/Controllers/MembresiaController.html#method_store","d":"<p>Almacena una nueva membres\u00eda en la base de datos</p>"},{"t":"M","n":"App\\Http\\Controllers\\MembresiaController::show","p":"App/Http/Controllers/MembresiaController.html#method_show","d":"<p>Muestra los detalles de una membres\u00eda espec\u00edfica</p>"},{"t":"M","n":"App\\Http\\Controllers\\MembresiaController::edit","p":"App/Http/Controllers/MembresiaController.html#method_edit","d":"<p>Muestra el formulario para editar una membres\u00eda existente</p>"},{"t":"M","n":"App\\Http\\Controllers\\MembresiaController::update","p":"App/Http/Controllers/MembresiaController.html#method_update","d":"<p>Actualiza los datos de una membres\u00eda espec\u00edfica en la base de datos</p>"},{"t":"M","n":"App\\Http\\Controllers\\MembresiaController::destroy","p":"App/Http/Controllers/MembresiaController.html#method_destroy","d":"<p>Elimina una membres\u00eda espec\u00edfica de la base de datos</p>"},{"t":"M","n":"App\\Http\\Controllers\\PagoController::index","p":"App/Http/Controllers/PagoController.html#method_index","d":"<p>Muestra el listado de pagos realizados</p>"},{"t":"M","n":"App\\Http\\Controllers\\PagoController::create","p":"App/Http/Controllers/PagoController.html#method_create","d":"<p>Muestra el formulario para registrar un nuevo pago</p>"},{"t":"M","n":"App\\Http\\Controllers\\PagoController::store","p":"App/Http/Controllers/PagoController.html#method_store","d":"<p>La funci\u00f3n <code>store</code> procesa una solicitud de pago, crea registros de pago y detalles de pago,\nactiva un cliente y maneja cualquier error que pueda ocurrir.</p>"},{"t":"M","n":"App\\Http\\Controllers\\PagoController::show","p":"App/Http/Controllers/PagoController.html#method_show","d":"<p>Muestra los detalles de un pago espec\u00edfico</p>"},{"t":"M","n":"App\\Http\\Controllers\\PagoController::edit","p":"App/Http/Controllers/PagoController.html#method_edit","d":"<p>Muestra el formulario para editar un pago</p>"},{"t":"M","n":"App\\Http\\Controllers\\PagoController::update","p":"App/Http/Controllers/PagoController.html#method_update","d":"<p>La funci\u00f3n <code>update</code> en PHP actualiza el pago y los detalles del pago, manejando la validaci\u00f3n y\nlas transacciones de la base de datos.</p>"},{"t":"M","n":"App\\Http\\Controllers\\PagoController::destroy","p":"App/Http/Controllers/PagoController.html#method_destroy","d":"<p>Elimina un pago de la base de datos</p>"},{"t":"M","n":"App\\Http\\Controllers\\PagoController::generarFactura","p":"App/Http/Controllers/PagoController.html#method_generarFactura","d":"<p>Genera un comprobante de pago en formato PDF</p>"},{"t":"M","n":"App\\Http\\Controllers\\PagodetallController::index","p":"App/Http/Controllers/PagodetallController.html#method_index","d":"<p>La funci\u00f3n index muestra el listado de pagodetalls</p>"},{"t":"M","n":"App\\Http\\Controllers\\PagodetallController::create","p":"App/Http/Controllers/PagodetallController.html#method_create","d":"<p>Muestra el formulario para registrar un nuevo pagodetall</p>"},{"t":"M","n":"App\\Http\\Controllers\\PagodetallController::store","p":"App/Http/Controllers/PagodetallController.html#method_store","d":"<p>La funci\u00f3n store almacena un nuevo pagodetall en la base de datos</p>"},{"t":"M","n":"App\\Http\\Controllers\\PagodetallController::show","p":"App/Http/Controllers/PagodetallController.html#method_show","d":"<p>La funci\u00f3n show muestra el recurso especificado por id</p>"},{"t":"M","n":"App\\Http\\Controllers\\PagodetallController::edit","p":"App/Http/Controllers/PagodetallController.html#method_edit","d":"<p>La funci\u00f3n edit muestra el formulario para editar el pagodetall especificado por id</p>"},{"t":"M","n":"App\\Http\\Controllers\\PagodetallController::update","p":"App/Http/Controllers/PagodetallController.html#method_update","d":"<p>La funci\u00f3n update actualiza los datos del pagodetall en la base de datos</p>"},{"t":"M","n":"App\\Http\\Controllers\\PagodetallController::destroy","p":"App/Http/Controllers/PagodetallController.html#method_destroy","d":"<p>La funci\u00f3n destroy elimina el pagodetall especificado por id</p>"},{"t":"M","n":"App\\Http\\Controllers\\PermisoController::index","p":"App/Http/Controllers/PermisoController.html#method_index","d":"<p>Muestra el listado de permisos y roles</p>"},{"t":"M","n":"App\\Http\\Controllers\\PermisoController::store","p":"App/Http/Controllers/PermisoController.html#method_store","d":"<p>Almacena un nuevo permiso en la base de datos</p>"},{"t":"M","n":"App\\Http\\Controllers\\PermisoController::update","p":"App/Http/Controllers/PermisoController.html#method_update","d":"<p>Actualiza un permiso en la base de datos</p>"},{"t":"M","n":"App\\Http\\Controllers\\PermisoController::destroy","p":"App/Http/Controllers/PermisoController.html#method_destroy","d":"<p>Elimina un permiso de la base de datos</p>"},{"t":"M","n":"App\\Http\\Controllers\\ProfileController::edit","p":"App/Http/Controllers/ProfileController.html#method_edit","d":"<p>Muestra el formulario de edici\u00f3n del perfil</p>"},{"t":"M","n":"App\\Http\\Controllers\\ProfileController::update","p":"App/Http/Controllers/ProfileController.html#method_update","d":"<p>Actualiza los datos del perfil del usuario</p>"},{"t":"M","n":"App\\Http\\Controllers\\ProfileController::updatePassword","p":"App/Http/Controllers/ProfileController.html#method_updatePassword","d":"<p>Actualiza la contrase\u00f1a del usuario</p>"},{"t":"M","n":"App\\Http\\Controllers\\ReporteController::index","p":"App/Http/Controllers/ReporteController.html#method_index","d":"<p>Muestra la vista principal para la generaci\u00f3n de reportes.</p>"},{"t":"M","n":"App\\Http\\Controllers\\ReporteController::generar","p":"App/Http/Controllers/ReporteController.html#method_generar","d":"<p>Genera un reporte PDF seg\u00fan el tipo especificado.</p>"},{"t":"M","n":"App\\Http\\Controllers\\RolController::index","p":"App/Http/Controllers/RolController.html#method_index","d":"<p>Muestra el listado de roles con sus permisos asociados</p>"},{"t":"M","n":"App\\Http\\Controllers\\RolController::store","p":"App/Http/Controllers/RolController.html#method_store","d":"<p>Almacena un nuevo rol en la base de datos</p>"},{"t":"M","n":"App\\Http\\Controllers\\RolController::update","p":"App/Http/Controllers/RolController.html#method_update","d":"<p>La funcion <code>update</code> en PHP maneja la actualizaci\u00f3n de una entidad de rol, incluyendo la verificaci\u00f3n\nde cambios en nombre, descripci\u00f3n y permisos, y el registro de cualquier error que ocurra.</p>"},{"t":"M","n":"App\\Http\\Controllers\\RolController::destroy","p":"App/Http/Controllers/RolController.html#method_destroy","d":"<p>Elimina un rol de la base de datos</p>"},{"t":"M","n":"App\\Http\\Controllers\\RolporpermisoController::index","p":"App/Http/Controllers/RolporpermisoController.html#method_index","d":"<p>La funci\u00f3n index obtiene y pagina los datos de Rolporpermiso con manejo de errores y logging.</p>"},{"t":"M","n":"App\\Http\\Controllers\\RolporpermisoController::create","p":"App/Http/Controllers/RolporpermisoController.html#method_create","d":"<p>La funci\u00f3n <code>create</code> recupera todos los roles y permisos y devuelve una vista con los datos.</p>"},{"t":"M","n":"App\\Http\\Controllers\\RolporpermisoController::store","p":"App/Http/Controllers/RolporpermisoController.html#method_store","d":"<p>La funci\u00f3n <code>store</code> almacena un nuevo recurso en la base de datos.</p>"},{"t":"M","n":"App\\Http\\Controllers\\RolporpermisoController::show","p":"App/Http/Controllers/RolporpermisoController.html#method_show","d":"<p>La funci\u00f3n <code>show</code> recupera un modelo Rolporpermiso espec\u00edfico por su ID y luego devuelve una vista\ncon los datos recuperados.</p>"},{"t":"M","n":"App\\Http\\Controllers\\RolporpermisoController::edit","p":"App/Http/Controllers/RolporpermisoController.html#method_edit","d":"<p>La funci\u00f3n <code>edit</code> recupera un modelo Rolporpermiso espec\u00edfico por su ID y luego devuelve una vista\ncon los datos recuperados.</p>"},{"t":"M","n":"App\\Http\\Controllers\\RolporpermisoController::update","p":"App/Http/Controllers/RolporpermisoController.html#method_update","d":"<p>La funci\u00f3n <code>update</code> actualiza los datos de un recurso en la base de datos.</p>"},{"t":"M","n":"App\\Http\\Controllers\\RolporpermisoController::destroy","p":"App/Http/Controllers/RolporpermisoController.html#method_destroy","d":null},{"t":"M","n":"App\\Http\\Controllers\\UserController::index","p":"App/Http/Controllers/UserController.html#method_index","d":"<p>Muestra el listado de usuarios con sus roles asociados</p>"},{"t":"M","n":"App\\Http\\Controllers\\UserController::create","p":"App/Http/Controllers/UserController.html#method_create","d":"<p>Muestra el formulario para crear un nuevo usuario</p>"},{"t":"M","n":"App\\Http\\Controllers\\UserController::store","p":"App/Http/Controllers/UserController.html#method_store","d":"<p>Almacena un nuevo usuario en la base de datos</p>"},{"t":"M","n":"App\\Http\\Controllers\\UserController::show","p":"App/Http/Controllers/UserController.html#method_show","d":"<p>Muestra los datos de un usuario</p>"},{"t":"M","n":"App\\Http\\Controllers\\UserController::edit","p":"App/Http/Controllers/UserController.html#method_edit","d":"<p>Muestra el formulario para editar un usuario</p>"},{"t":"M","n":"App\\Http\\Controllers\\UserController::update","p":"App/Http/Controllers/UserController.html#method_update","d":"<p>Actualiza los datos de un usuario</p>"},{"t":"M","n":"App\\Http\\Controllers\\UserController::destroy","p":"App/Http/Controllers/UserController.html#method_destroy","d":"<p>Elimina un usuario de la base de datos</p>"},{"t":"M","n":"App\\Http\\Middleware\\Authenticate::redirectTo","p":"App/Http/Middleware/Authenticate.html#method_redirectTo","d":"<p>Obtiene la ruta a la que se debe redirigir al usuario cuando no est\u00e1 autenticado</p>"},{"t":"M","n":"App\\Http\\Middleware\\CheckPermiso::handle","p":"App/Http/Middleware/CheckPermiso.html#method_handle","d":"<p>Maneja la petici\u00f3n entrante verificando los permisos</p>"},{"t":"M","n":"App\\Http\\Requests\\BitacoracambioRequest::authorize","p":"App/Http/Requests/BitacoracambioRequest.html#method_authorize","d":"<p>Determina si el usuario est\u00e1 autorizado para realizar esta solicitud</p>"},{"t":"M","n":"App\\Http\\Requests\\BitacoracambioRequest::rules","p":"App/Http/Requests/BitacoracambioRequest.html#method_rules","d":"<p>Obtiene las reglas de validaci\u00f3n aplicables a la solicitud</p>"},{"t":"M","n":"App\\Http\\Requests\\ClienteRequest::authorize","p":"App/Http/Requests/ClienteRequest.html#method_authorize","d":"<p>Determina si el usuario est\u00e1 autorizado para realizar esta solicitud</p>"},{"t":"M","n":"App\\Http\\Requests\\ClienteRequest::rules","p":"App/Http/Requests/ClienteRequest.html#method_rules","d":"<p>Obtiene las reglas de validaci\u00f3n aplicables a la solicitud</p>"},{"t":"M","n":"App\\Http\\Requests\\EmpleadoRequest::authorize","p":"App/Http/Requests/EmpleadoRequest.html#method_authorize","d":"<p>Determina si el usuario est\u00e1 autorizado para realizar esta solicitud</p>"},{"t":"M","n":"App\\Http\\Requests\\EmpleadoRequest::rules","p":"App/Http/Requests/EmpleadoRequest.html#method_rules","d":"<p>Obtiene las reglas de validaci\u00f3n aplicables a la solicitud</p>"},{"t":"M","n":"App\\Http\\Requests\\MembresiaRequest::authorize","p":"App/Http/Requests/MembresiaRequest.html#method_authorize","d":"<p>Determina si el usuario est\u00e1 autorizado para realizar esta solicitud</p>"},{"t":"M","n":"App\\Http\\Requests\\MembresiaRequest::rules","p":"App/Http/Requests/MembresiaRequest.html#method_rules","d":"<p>Obtiene las reglas de validaci\u00f3n aplicables a la solicitud</p>"},{"t":"M","n":"App\\Http\\Requests\\PagoRequest::authorize","p":"App/Http/Requests/PagoRequest.html#method_authorize","d":"<p>Determina si el usuario est\u00e1 autorizado para realizar esta solicitud</p>"},{"t":"M","n":"App\\Http\\Requests\\PagoRequest::rules","p":"App/Http/Requests/PagoRequest.html#method_rules","d":"<p>Obtiene las reglas de validaci\u00f3n aplicables a la solicitud</p>"},{"t":"M","n":"App\\Http\\Requests\\PagodetallRequest::authorize","p":"App/Http/Requests/PagodetallRequest.html#method_authorize","d":"<p>Determina si el usuario est\u00e1 autorizado para realizar esta solicitud</p>"},{"t":"M","n":"App\\Http\\Requests\\PagodetallRequest::rules","p":"App/Http/Requests/PagodetallRequest.html#method_rules","d":"<p>Obtiene las reglas de validaci\u00f3n aplicables a la solicitud</p>"},{"t":"M","n":"App\\Http\\Requests\\PermisoRequest::authorize","p":"App/Http/Requests/PermisoRequest.html#method_authorize","d":"<p>Determina si el usuario est\u00e1 autorizado para realizar esta solicitud</p>"},{"t":"M","n":"App\\Http\\Requests\\PermisoRequest::rules","p":"App/Http/Requests/PermisoRequest.html#method_rules","d":"<p>Obtiene las reglas de validaci\u00f3n aplicables a la solicitud</p>"},{"t":"M","n":"App\\Http\\Requests\\RolRequest::authorize","p":"App/Http/Requests/RolRequest.html#method_authorize","d":"<p>Determina si el usuario est\u00e1 autorizado para realizar esta solicitud</p>"},{"t":"M","n":"App\\Http\\Requests\\RolRequest::rules","p":"App/Http/Requests/RolRequest.html#method_rules","d":"<p>Obtiene las reglas de validaci\u00f3n aplicables a la solicitud</p>"},{"t":"M","n":"App\\Http\\Requests\\RolporpermisoRequest::authorize","p":"App/Http/Requests/RolporpermisoRequest.html#method_authorize","d":"<p>Determina si el usuario est\u00e1 autorizado para realizar esta solicitud</p>"},{"t":"M","n":"App\\Http\\Requests\\RolporpermisoRequest::rules","p":"App/Http/Requests/RolporpermisoRequest.html#method_rules","d":"<p>Obtiene las reglas de validaci\u00f3n aplicables a la solicitud</p>"},{"t":"M","n":"App\\Models\\Bitacoracambio::getBadgeClass","p":"App/Models/Bitacoracambio.html#method_getBadgeClass","d":"<p>Obtiene la clase CSS del badge seg\u00fan el tipo de acci\u00f3n</p>"},{"t":"M","n":"App\\Models\\Bitacoracambio::newModelQuery","p":"App/Models/Bitacoracambio.html#method_newModelQuery","d":""},{"t":"M","n":"App\\Models\\Bitacoracambio::newQuery","p":"App/Models/Bitacoracambio.html#method_newQuery","d":""},{"t":"M","n":"App\\Models\\Bitacoracambio::query","p":"App/Models/Bitacoracambio.html#method_query","d":""},{"t":"M","n":"App\\Models\\Cliente::pagos","p":"App/Models/Cliente.html#method_pagos","d":"<p>La funci\u00f3n pagos() establece una relaci\u00f3n entre el modelo Cliente y el modelo Pago</p>"},{"t":"M","n":"App\\Models\\Cliente::membresias","p":"App/Models/Cliente.html#method_membresias","d":"<p>Relaci\u00f3n con las membres\u00edas a trav\u00e9s de los detalles de pago</p>"},{"t":"M","n":"App\\Models\\Cliente::newModelQuery","p":"App/Models/Cliente.html#method_newModelQuery","d":""},{"t":"M","n":"App\\Models\\Cliente::newQuery","p":"App/Models/Cliente.html#method_newQuery","d":""},{"t":"M","n":"App\\Models\\Cliente::query","p":"App/Models/Cliente.html#method_query","d":""},{"t":"M","n":"App\\Models\\Cliente::onlyTrashed","p":"App/Models/Cliente.html#method_onlyTrashed","d":""},{"t":"M","n":"App\\Models\\Cliente::withTrashed","p":"App/Models/Cliente.html#method_withTrashed","d":""},{"t":"M","n":"App\\Models\\Empleado::newModelQuery","p":"App/Models/Empleado.html#method_newModelQuery","d":""},{"t":"M","n":"App\\Models\\Empleado::newQuery","p":"App/Models/Empleado.html#method_newQuery","d":""},{"t":"M","n":"App\\Models\\Empleado::query","p":"App/Models/Empleado.html#method_query","d":""},{"t":"M","n":"App\\Models\\Empleado::onlyTrashed","p":"App/Models/Empleado.html#method_onlyTrashed","d":""},{"t":"M","n":"App\\Models\\Empleado::withTrashed","p":"App/Models/Empleado.html#method_withTrashed","d":""},{"t":"M","n":"App\\Models\\Membresia::pagodetalls","p":"App/Models/Membresia.html#method_pagodetalls","d":""},{"t":"M","n":"App\\Models\\Pago::cliente","p":"App/Models/Pago.html#method_cliente","d":"<p>Relaci\u00f3n con Cliente</p>"},{"t":"M","n":"App\\Models\\Pago::detalles","p":"App/Models/Pago.html#method_detalles","d":"<p>Relaci\u00f3n con PagoDetalle</p>"},{"t":"M","n":"App\\Models\\Pago::getDiasRestantesAttribute","p":"App/Models/Pago.html#method_getDiasRestantesAttribute","d":"<p>Calcula los d\u00edas restantes de la membres\u00eda</p>"},{"t":"M","n":"App\\Models\\Pago::scopePorMetodoPago","p":"App/Models/Pago.html#method_scopePorMetodoPago","d":"<p>Scope para filtrar pagos por m\u00e9todo de pago</p>"},{"t":"M","n":"App\\Models\\Pago::scopeEntreFechas","p":"App/Models/Pago.html#method_scopeEntreFechas","d":"<p>Scope para filtrar pagos por rango de fechas</p>"},{"t":"M","n":"App\\Models\\Pago::getTotalFormateadoAttribute","p":"App/Models/Pago.html#method_getTotalFormateadoAttribute","d":"<p>Formatea el total como moneda</p>"},{"t":"M","n":"App\\Models\\Pagodetall::pago","p":"App/Models/Pagodetall.html#method_pago","d":""},{"t":"M","n":"App\\Models\\Pagodetall::membresia","p":"App/Models/Pagodetall.html#method_membresia","d":""},{"t":"M","n":"App\\Models\\Permiso::roles","p":"App/Models/Permiso.html#method_roles","d":"<p>Obtiene los roles asociados al permiso</p>"},{"t":"M","n":"App\\Models\\Permiso::rolporpermisos","p":"App/Models/Permiso.html#method_rolporpermisos","d":"<p>Obtiene las asignaciones de roles y permisos</p>"},{"t":"M","n":"App\\Models\\Rol::rolporpermisos","p":"App/Models/Rol.html#method_rolporpermisos","d":"<p>Obtiene los permisos del rol a trav\u00e9s de la tabla pivote</p>"},{"t":"M","n":"App\\Models\\Rol::permisos","p":"App/Models/Rol.html#method_permisos","d":"<p>Obtiene los permisos asociados al rol</p>"},{"t":"M","n":"App\\Models\\Rol::hasPermiso","p":"App/Models/Rol.html#method_hasPermiso","d":"<p>Verifica si el rol tiene un permiso espec\u00edfico</p>"},{"t":"M","n":"App\\Models\\Rolporpermiso::permiso","p":"App/Models/Rolporpermiso.html#method_permiso","d":""},{"t":"M","n":"App\\Models\\Rolporpermiso::rol","p":"App/Models/Rolporpermiso.html#method_rol","d":""},{"t":"M","n":"App\\Models\\User::casts","p":"App/Models/User.html#method_casts","d":"<p>Los atributos que deben ser convertidos a tipos nativos</p>"},{"t":"M","n":"App\\Models\\User::rol","p":"App/Models/User.html#method_rol","d":"<p>Obtiene el rol asociado al usuario</p>"},{"t":"M","n":"App\\Models\\User::hasPermiso","p":"App/Models/User.html#method_hasPermiso","d":"<p>La funci\u00f3n <code>hasPermiso</code> verifica si un usuario tiene un permiso espec\u00edfico asignado basado en su\nrol.</p>"},{"t":"M","n":"App\\Models\\User::hasRol","p":"App/Models/User.html#method_hasRol","d":"<p>La funci\u00f3n <code>hasRol</code> verifica si un usuario tiene un rol espec\u00edfico asignado.</p>"},{"t":"M","n":"App\\Providers\\AppServiceProvider::register","p":"App/Providers/AppServiceProvider.html#method_register","d":"<p>Registra los servicios de la aplicaci\u00f3n</p>"},{"t":"M","n":"App\\Providers\\AppServiceProvider::boot","p":"App/Providers/AppServiceProvider.html#method_boot","d":"<p>Inicializa los servicios de la aplicaci\u00f3n</p>"},{"t":"M","n":"App\\Traits\\RegistraBitacora::bootRegistraBitacora","p":"App/Traits/RegistraBitacora.html#method_bootRegistraBitacora","d":"<p>Inicializa los observadores del modelo</p>"},{"t":"M","n":"App\\Traits\\RegistraBitacora::registrarCambio","p":"App/Traits/RegistraBitacora.html#method_registrarCambio","d":"<p>Registra un cambio en la bit\u00e1cora</p>"},{"t":"N","n":"App","p":"App.html"},{"t":"N","n":"App\\Http","p":"App/Http.html"},{"t":"N","n":"App\\Http\\Controllers","p":"App/Http/Controllers.html"},{"t":"N","n":"App\\Http\\Controllers\\Auth","p":"App/Http/Controllers/Auth.html"},{"t":"N","n":"App\\Http\\Middleware","p":"App/Http/Middleware.html"},{"t":"N","n":"App\\Http\\Requests","p":"App/Http/Requests.html"},{"t":"N","n":"App\\Models","p":"App/Models.html"},{"t":"N","n":"App\\Providers","p":"App/Providers.html"},{"t":"N","n":"App\\Traits","p":"App/Traits.html"}]}
